CHANGELOG.txt
LICENSE.txt
MANIFEST.in
README.txt
setup.py
syscomm/__init__.py
syscomm.egg-info/PKG-INFO
syscomm.egg-info/SOURCES.txt
syscomm.egg-info/dependency_links.txt
syscomm.egg-info/top_level.txt