Metadata-Version: 1.1
Name: syscomm
Version: 0.0.1
Summary: A module to use cmd commands in python
Home-page: UNKNOWN
Author: Luke Dixon
Author-email: monkeyodixon@gmail.com
License: MIT
Keywords: system
Platform: UNKNOWN
Classifier: Development Status :: 5 - Production/Stable
Classifier: Intended Audience :: Education
Classifier: Operating System :: Microsoft :: Windows :: Windows 10
Classifier: License :: OSI Approved :: MIT License
Classifier: Programming Language :: Python :: 3
